tyjuliacall/__init__.py
tyjuliasetup/Project.toml
tyjuliasetup/__init__.py
tyjuliasetup/compat.py
tyjuliasetup/julia_src_binding.py
tyjuliasetup/jv.py
tyjuliasetup/src/TyJuliaSetup.jl
tyjuliacall-0.7.5.dist-info/LICENSE
tyjuliacall-0.7.5.dist-info/METADATA
tyjuliacall-0.7.5.dist-info/WHEEL
tyjuliacall-0.7.5.dist-info/RECORD
