Metadata-Version: 2.3
Name: tyjuliacall
Version: 0.7.5
Summary: Python-Julia interops.
Author: Suzhou-Tongyuan
Author-email: support@tongyuan.cc
Requires-Python: >=3.7,<4.0
Classifier: Programming Language :: Python :: 3
Classifier: Programming Language :: Python :: 3.7
Classifier: Programming Language :: Python :: 3.8
Classifier: Programming Language :: Python :: 3.9
Classifier: Programming Language :: Python :: 3.10
Classifier: Programming Language :: Python :: 3.11
Classifier: Programming Language :: Python :: 3.12
Classifier: Programming Language :: Python :: 3.13
Requires-Dist: julia-numpy (>=0.4.3,<0.5.0)
